crush/__init__.py
crush/analyze.py
crush/compare.py
crush/main.py
crush/optimize.py
crush/libcrush.cpython-34m.so
crush/ceph/__init__.py
crush/ceph/convert.py
crush/libcrush/CMakeLists.txt
crush/libcrush/ceph_read_write.cc
crush/libcrush/ceph_read_write.h
crush/libcrush/config-h.in.cmake
crush/libcrush/libcrush.c
crush/libcrush/libcrush.h
crush/libcrush/module.c
crush/libcrush/common/Formatter.cc
crush/libcrush/common/Formatter.h
crush/libcrush/common/HTMLFormatter.cc
crush/libcrush/common/HTMLFormatter.h
crush/libcrush/common/armor.c
crush/libcrush/common/armor.h
crush/libcrush/common/buffer.cc
crush/libcrush/common/compiler_extensions.h
crush/libcrush/common/debug.h
crush/libcrush/common/deleter.h
crush/libcrush/common/errno.cc
crush/libcrush/common/errno.h
crush/libcrush/common/escape.c
crush/libcrush/common/escape.h
crush/libcrush/common/likely.h
crush/libcrush/common/mempool.cc
crush/libcrush/common/page.cc
crush/libcrush/common/safe_io.c
crush/libcrush/common/safe_io.h
crush/libcrush/common/simple_spin.h
crush/libcrush/common/strtol.cc
crush/libcrush/common/strtol.h
crush/libcrush/common/valgrind.h
crush/libcrush/crush/CrushCompiler.cc
crush/libcrush/crush/CrushCompiler.h
crush/libcrush/crush/CrushTreeDumper.h
crush/libcrush/crush/CrushWrapper.cc
crush/libcrush/crush/CrushWrapper.h
crush/libcrush/crush/CrushWrapper.i
crush/libcrush/crush/builder.c
crush/libcrush/crush/builder.h
crush/libcrush/crush/crush.c
crush/libcrush/crush/crush.h
crush/libcrush/crush/crush_compat.h
crush/libcrush/crush/crush_ln_table.h
crush/libcrush/crush/grammar.h
crush/libcrush/crush/hash.c
crush/libcrush/crush/hash.h
crush/libcrush/crush/mapper.c
crush/libcrush/crush/mapper.h
crush/libcrush/crush/types.h
crush/libcrush/include/Spinlock.h
crush/libcrush/include/atomic.h
crush/libcrush/include/buffer.h
crush/libcrush/include/buffer_fwd.h
crush/libcrush/include/byteorder.h
crush/libcrush/include/ceph_features.h
crush-1.0.35.dist-info/DESCRIPTION.rst
crush-1.0.35.dist-info/metadata.json
crush-1.0.35.dist-info/top_level.txt
crush-1.0.35.dist-info/WHEEL
crush-1.0.35.dist-info/METADATA
crush-1.0.35.dist-info/RECORD
