Metadata-Version: 2.0
Name: crush
Version: 1.0.35
Summary: library to control placement in a hierarchy
Home-page: http://libcrush.org/main/python-crush
Author: Loic Dachary
Author-email: loic@dachary.org
License: UNKNOWN
Platform: UNKNOWN
Classifier: Environment :: Console
Classifier: Intended Audience :: Information Technology
Classifier: Intended Audience :: System Administrators
Classifier: Operating System :: POSIX :: Linux
Classifier: License :: OSI Approved :: GNU General Public License v3 or later (GPLv3+)
Classifier: Programming Language :: Python
Classifier: Programming Language :: Python :: 2
Classifier: Programming Language :: Python :: 3
Classifier: Topic :: Utilities
Requires-Dist: appdirs (==1.4.3)
Requires-Dist: d2to1 (==0.2.12.post1)
Requires-Dist: numpy (==1.12.1)
Requires-Dist: packaging (==16.8)
Requires-Dist: pandas (==0.19.2)
Requires-Dist: pbr (==3.0.0)
Requires-Dist: pyparsing (==2.2.0)
Requires-Dist: python-dateutil (==2.6.0)
Requires-Dist: pytz (==2017.2)
Requires-Dist: six (==1.10.0)
